<?xml version="1.0" encoding="UTF-8" standalone="yes" ?>
<schema
  xmlns="http://freighttrust.io/EDISchema/v4"
  xmlns:xsi="http://www.w3.org/2001/XMLSchema-instance"
  xsi:schemaLocation="http://freighttrust.io/EDISchema/v4 https://www.freighttrust.io/EDISchema/EDISchema-v4.xsd"
>
    <transaction>
        <sequence>
            <segment type="BGN" />
            <loop code="L0001" minOccurs="1" maxOccurs="99999">
                <sequence>
                    <segment type="N1" />
                    <segment type="N2" />
                    <segment type="N3" maxOccurs="2" />
                    <segment type="N4" />
                </sequence>
            </loop>
            <segment type="N9" maxOccurs="10" />
            <segment type="G61" maxOccurs="99999" />
            <segment type="NTE" maxOccurs="20" />
            <segment type="G93" maxOccurs="50" />
            <segment type="G62" minOccurs="1" />
            <segment type="LDT" maxOccurs="99999" />
            <loop code="L0002" maxOccurs="99999">
                <sequence>
                    <segment type="LM" />
                    <segment type="LQ" minOccurs="1" maxOccurs="100" />
                </sequence>
            </loop>
            <loop code="L0003" minOccurs="1" maxOccurs="99999">
                <sequence>
                    <segment type="G53" />
                    <segment type="G62" maxOccurs="3" />
                    <segment type="NTE" maxOccurs="20" />
                    <loop code="L0004" minOccurs="1" maxOccurs="99999">
                        <sequence>
                            <segment type="LX" />
                            <segment type="G39" />
                            <segment type="USI" />
                            <segment type="G69" maxOccurs="5" />
                            <segment type="QTY" maxOccurs="99999" />
                            <segment type="LIN" />
                            <segment type="PID" maxOccurs="200" />
                            <segment type="PKG" maxOccurs="25" />
                            <segment type="G23" maxOccurs="10" />
                            <segment type="G62" maxOccurs="2" />
                            <segment type="G36" />
                            <segment type="G26" maxOccurs="2" />
                            <segment type="G43" maxOccurs="9999" />
                            <segment type="G24" maxOccurs="999" />
                            <segment type="G40" maxOccurs="99" />
                            <segment type="G93" maxOccurs="50" />
                            <segment type="G22" maxOccurs="5" />
                            <segment type="G46" maxOccurs="99" />
                            <segment type="H1" maxOccurs="5" />
                            <segment type="G54" maxOccurs="99" />
                            <segment type="N9" maxOccurs="10" />
                            <segment type="UIT" maxOccurs="10" />
                            <segment type="MEA" maxOccurs="10" />
                            <segment type="TD1" />
                            <segment type="TD4" maxOccurs="99999" />
                            <segment type="LDT" />
                            <loop code="L0005" maxOccurs="99999">
<sequence>
    <segment type="N1" />
    <segment type="N2" maxOccurs="2" />
    <segment type="N3" maxOccurs="2" />
    <segment type="N4" />
    <segment type="PAL" maxOccurs="99999" />
    <segment type="G93" />
    <segment type="QTY" />
</sequence>
                            </loop>
                            <loop code="L0006" maxOccurs="99999">
<sequence>
    <segment type="G55" />
    <segment type="G69" maxOccurs="5" />
    <segment type="QTY" />
    <segment type="LIN" />
    <segment type="PID" maxOccurs="200" />
    <segment type="H1" maxOccurs="5" />
    <segment type="REF" maxOccurs="10" />
    <segment type="PKG" maxOccurs="25" />
    <segment type="MEA" maxOccurs="10" />
    <segment type="TD1" />
    <segment type="TD4" maxOccurs="99999" />
    <segment type="SLN" maxOccurs="100" />
    <segment type="LDT" />
</sequence>
                            </loop>
                            <loop code="L0007" maxOccurs="99999">
<sequence>
    <segment type="LM" />
    <segment type="LQ" minOccurs="1" maxOccurs="100" />
</sequence>
                            </loop>
                        </sequence>
                    </loop>
                </sequence>
            </loop>
        </sequence>
    </transaction>
    <elementType name="BGN01" base="string" minLength="2" maxLength="2" />
    <elementType name="BGN02" base="string" maxLength="80" />
    <elementType name="BGN03" base="date" minLength="8" maxLength="8" />
    <elementType name="BGN04" base="time" minLength="4" maxLength="8" />
    <elementType name="BGN05" base="string" minLength="2" maxLength="2" />
    <elementType name="BGN06" base="string" maxLength="80" />
    <elementType name="BGN07" base="string" minLength="2" maxLength="2" />
    <elementType name="BGN08" base="string" maxLength="2" />
    <elementType name="BGN09" base="string" minLength="2" maxLength="2" />
    <elementType name="G2201" base="string" />
    <elementType name="G2202" base="numeric" scale="2" minLength="2" maxLength="7" />
    <elementType name="G2203" base="decimal" maxLength="2" />
    <elementType name="G2204" base="string" maxLength="60" />
    <elementType name="G2205" base="date" minLength="8" maxLength="8" />
    <elementType name="G2301" base="string" minLength="2" maxLength="2" />
    <elementType name="G2302" base="string" maxLength="2" />
    <elementType name="G2303" base="date" minLength="8" maxLength="8" />
    <elementType name="G2304" base="string" minLength="2" maxLength="2" />
    <elementType name="G2305" base="decimal" maxLength="6" />
    <elementType name="G2306" base="date" minLength="8" maxLength="8" />
    <elementType name="G2307" base="decimal" maxLength="3" />
    <elementType name="G2308" base="date" minLength="8" maxLength="8" />
    <elementType name="G2309" base="decimal" maxLength="3" />
    <elementType name="G2310" base="numeric" scale="2" maxLength="10" />
    <elementType name="G2311" base="numeric" scale="2" maxLength="10" />
    <elementType name="G2312" base="numeric" scale="2" maxLength="10" />
    <elementType name="G2313" base="numeric" scale="2" maxLength="10" />
    <elementType name="G2314" base="decimal" maxLength="5" />
    <elementType name="G2315" base="string" maxLength="60" />
    <elementType name="G2316" base="decimal" minLength="2" maxLength="2" />
    <elementType name="G2401" base="string" maxLength="16" />
    <elementType name="G2601" base="string" minLength="2" maxLength="2" />
    <elementType name="G2602" base="string" minLength="2" maxLength="2" />
    <elementType name="G2603" base="date" minLength="8" maxLength="8" />
    <elementType name="G2604" base="string" minLength="3" maxLength="3" />
    <elementType name="G2605" base="decimal" maxLength="15" />
    <elementType name="G2606" base="string" minLength="2" maxLength="2" />
    <elementType name="G3601" base="string" maxLength="16" />
    <elementType name="G3602" base="string" maxLength="16" />
    <elementType name="G3603" base="date" minLength="8" maxLength="8" />
    <elementType name="G3604" base="string" minLength="3" maxLength="3" />
    <elementType name="G3901" base="string" minLength="12" maxLength="12" />
    <elementType name="G3902" base="string" minLength="2" maxLength="2" />
    <elementType name="G3903" base="string" maxLength="80" />
    <elementType name="G3904" base="string" minLength="2" maxLength="3" />
    <elementType name="G3905" base="decimal" maxLength="8" />
    <elementType name="G3906" base="string" maxLength="2" />
    <elementType name="G3907" base="string" />
    <elementType name="G3908" base="decimal" maxLength="8" />
    <elementType name="G3909" base="string" minLength="2" maxLength="2" />
    <elementType name="G3910" base="decimal" maxLength="8" />
    <elementType name="G3911" base="string" minLength="2" maxLength="2" />
    <elementType name="G3912" base="decimal" maxLength="8" />
    <elementType name="G3913" base="string" minLength="2" maxLength="2" />
    <elementType name="G3914" base="decimal" maxLength="8" />
    <elementType name="G3915" base="string" minLength="2" maxLength="2" />
    <elementType name="G3916" base="decimal" minLength="6" maxLength="6" />
    <elementType name="G3917" base="decimal" maxLength="6" />
    <elementType name="G3918" base="decimal" maxLength="8" />
    <elementType name="G3919" base="string" minLength="2" maxLength="2" />
    <elementType name="G3920" base="string" maxLength="10" />
    <elementType name="G3921" base="decimal" maxLength="10" />
    <elementType name="G3922" base="string" maxLength="3" />
    <elementType name="G3923" base="string" minLength="2" maxLength="2" />
    <elementType name="G3924" base="string" maxLength="80" />
    <elementType name="G3925" base="string" maxLength="2" />
    <elementType name="G3926" base="decimal" maxLength="8" />
    <elementType name="G3927" base="decimal" maxLength="6" />
    <elementType name="G3928" base="string" minLength="3" maxLength="5" />
    <elementType name="G3929" base="string" maxLength="20" />
    <elementType name="G4001" base="string" maxLength="3" />
    <elementType name="G4002" base="decimal" maxLength="9" />
    <elementType name="G4003" base="decimal" maxLength="9" />
    <elementType name="G4004" base="string" maxLength="45" />
    <elementType name="G4005" base="numeric" scale="2" minLength="2" maxLength="7" />
    <elementType name="G4006" base="numeric" scale="2" minLength="2" maxLength="7" />
    <elementType name="G4007" base="string" minLength="2" maxLength="2" />
    <elementType name="G4008" base="string" minLength="3" maxLength="3" />
    <elementType name="G4009" base="decimal" maxLength="9" />
    <elementType name="G4301" base="string" maxLength="3" />
    <elementType name="G4302" base="string" maxLength="13" />
    <elementType name="G4303" base="string" maxLength="80" />
    <elementType name="G4304" base="string" minLength="2" maxLength="2" />
    <elementType name="G4601" base="string" maxLength="3" />
    <elementType name="G4602" base="string" minLength="2" maxLength="2" />
    <elementType name="G4603" base="decimal" maxLength="15" />
    <elementType name="G4604" base="string" minLength="2" maxLength="2" />
    <elementType name="G4605" base="numeric" scale="2" maxLength="15" />
    <elementType name="G4606" base="string" />
    <elementType name="G4607" base="decimal" maxLength="6" />
    <elementType name="G4608" base="string" maxLength="16" />
    <elementType name="G4609" base="string" maxLength="20" />
    <elementType name="G4610" base="string" maxLength="80" />
    <elementType name="G4611" base="string" minLength="3" maxLength="3" />
    <elementType name="G4612" base="decimal" maxLength="9" />
    <elementType name="G5301" base="string" minLength="3" maxLength="3" />
    <elementType name="G5401" base="decimal" maxLength="15" />
    <elementType name="G5402" base="string" minLength="2" maxLength="2" />
    <elementType name="G5403" base="string" minLength="12" maxLength="12" />
    <elementType name="G5404" base="string" minLength="2" maxLength="2" />
    <elementType name="G5405" base="string" maxLength="80" />
    <elementType name="G5406" base="string" maxLength="45" />
    <elementType name="G5501" base="string" minLength="2" maxLength="2" />
    <elementType name="G5502" base="string" maxLength="80" />
    <elementType name="G5503" base="string" minLength="2" maxLength="2" />
    <elementType name="G5504" base="string" maxLength="80" />
    <elementType name="G5505" base="decimal" maxLength="8" />
    <elementType name="G5506" base="string" minLength="2" maxLength="2" />
    <elementType name="G5507" base="decimal" maxLength="8" />
    <elementType name="G5508" base="string" minLength="2" maxLength="2" />
    <elementType name="G5509" base="decimal" maxLength="8" />
    <elementType name="G5510" base="string" minLength="2" maxLength="2" />
    <elementType name="G5511" base="decimal" maxLength="8" />
    <elementType name="G5512" base="string" minLength="2" maxLength="2" />
    <elementType name="G5513" base="decimal" maxLength="6" />
    <elementType name="G5514" base="decimal" maxLength="8" />
    <elementType name="G5515" base="string" minLength="2" maxLength="2" />
    <elementType name="G5516" base="string" maxLength="20" />
    <elementType name="G5517" base="string" maxLength="20" />
    <elementType name="G5518" base="string" minLength="3" maxLength="3" />
    <elementType name="G5519" base="decimal" maxLength="4" />
    <elementType name="G5520" base="decimal" maxLength="8" />
    <elementType name="G5521" base="string" />
    <elementType name="G5522" base="string" maxLength="10" />
    <elementType name="G5523" base="decimal" maxLength="8" />
    <elementType name="G5524" base="string" maxLength="2" />
    <elementType name="G5525" base="string" />
    <elementType name="G5526" base="decimal" maxLength="8" />
    <elementType name="G5527" base="string" maxLength="2" />
    <elementType name="G5528" base="string" />
    <elementType name="G5529" base="string" minLength="2" maxLength="2" />
    <elementType name="G5530" base="string" maxLength="80" />
    <elementType name="G5531" base="string" maxLength="45" />
    <elementType name="G5532" base="decimal" maxLength="6" />
    <elementType name="G5533" base="string" minLength="3" maxLength="5" />
    <elementType name="G6101" base="string" minLength="2" maxLength="2" />
    <elementType name="G6102" base="string" maxLength="60" />
    <elementType name="G6103" base="string" minLength="2" maxLength="2" />
    <elementType name="G6104" base="string" maxLength="256" />
    <elementType name="G6105" base="string" maxLength="20" />
    <elementType name="G6201" base="string" minLength="2" maxLength="2" />
    <elementType name="G6202" base="date" minLength="8" maxLength="8" />
    <elementType name="G6203" base="string" maxLength="2" />
    <elementType name="G6204" base="time" minLength="4" maxLength="8" />
    <elementType name="G6205" base="string" minLength="2" maxLength="2" />
    <elementType name="G6901" base="string" maxLength="45" />
    <elementType name="G9301" base="string" maxLength="3" />
    <elementType name="G9302" base="decimal" maxLength="15" />
    <elementType name="G9303" base="string" minLength="2" maxLength="2" />
    <elementType name="G9304" base="string" maxLength="45" />
    <elementType name="G9305" base="string" maxLength="2" />
    <elementType name="G9306" base="string" minLength="3" maxLength="3" />
    <elementType name="G9307" base="string" maxLength="2" />
    <elementType name="G9308" base="string" />
    <elementType name="H101" base="string" minLength="4" maxLength="10" />
    <elementType name="H102" base="string" maxLength="4" />
    <elementType name="H103" base="string" />
    <elementType name="H104" base="string" minLength="2" maxLength="30" />
    <elementType name="H105" base="string" maxLength="24" />
    <elementType name="H106" base="string" maxLength="6" />
    <elementType name="H107" base="decimal" maxLength="3" />
    <elementType name="H108" base="string" minLength="2" maxLength="2" />
    <elementType name="H109" base="string" maxLength="3" />
    <elementType name="LDT01" base="string" minLength="2" maxLength="2" />
    <elementType name="LDT02" base="decimal" maxLength="15" />
    <elementType name="LDT03" base="string" minLength="2" maxLength="2" />
    <elementType name="LDT04" base="date" minLength="8" maxLength="8" />
    <elementType name="LIN01" base="string" maxLength="20" />
    <elementType name="LIN02" base="string" minLength="2" maxLength="2" />
    <elementType name="LIN03" base="string" maxLength="80" />
    <elementType name="LIN04" base="string" minLength="2" maxLength="2" />
    <elementType name="LIN05" base="string" maxLength="80" />
    <elementType name="LIN06" base="string" minLength="2" maxLength="2" />
    <elementType name="LIN07" base="string" maxLength="80" />
    <elementType name="LIN08" base="string" minLength="2" maxLength="2" />
    <elementType name="LIN09" base="string" maxLength="80" />
    <elementType name="LIN10" base="string" minLength="2" maxLength="2" />
    <elementType name="LIN11" base="string" maxLength="80" />
    <elementType name="LIN12" base="string" minLength="2" maxLength="2" />
    <elementType name="LIN13" base="string" maxLength="80" />
    <elementType name="LIN14" base="string" minLength="2" maxLength="2" />
    <elementType name="LIN15" base="string" maxLength="80" />
    <elementType name="LIN16" base="string" minLength="2" maxLength="2" />
    <elementType name="LIN17" base="string" maxLength="80" />
    <elementType name="LIN18" base="string" minLength="2" maxLength="2" />
    <elementType name="LIN19" base="string" maxLength="80" />
    <elementType name="LIN20" base="string" minLength="2" maxLength="2" />
    <elementType name="LIN21" base="string" maxLength="80" />
    <elementType name="LIN22" base="string" minLength="2" maxLength="2" />
    <elementType name="LIN23" base="string" maxLength="80" />
    <elementType name="LIN24" base="string" minLength="2" maxLength="2" />
    <elementType name="LIN25" base="string" maxLength="80" />
    <elementType name="LIN26" base="string" minLength="2" maxLength="2" />
    <elementType name="LIN27" base="string" maxLength="80" />
    <elementType name="LIN28" base="string" minLength="2" maxLength="2" />
    <elementType name="LIN29" base="string" maxLength="80" />
    <elementType name="LIN30" base="string" minLength="2" maxLength="2" />
    <elementType name="LIN31" base="string" maxLength="80" />
    <elementType name="LM01" base="string" minLength="2" maxLength="2" />
    <elementType name="LM02" base="string" maxLength="15" />
    <elementType name="LQ01" base="string" maxLength="3" />
    <elementType name="LQ02" base="string" maxLength="30" />
    <elementType name="LX01" base="decimal" maxLength="6" />
    <elementType name="MEA01" base="string" minLength="2" maxLength="2" />
    <elementType name="MEA02" base="string" maxLength="3" />
    <elementType name="MEA03" base="decimal" maxLength="20" />
    <elementType name="MEA0401" base="string" minLength="2" maxLength="2" />
    <elementType name="MEA0402" base="decimal" maxLength="15" />
    <elementType name="MEA0403" base="decimal" maxLength="10" />
    <elementType name="MEA0404" base="string" minLength="2" maxLength="2" />
    <elementType name="MEA0405" base="decimal" maxLength="15" />
    <elementType name="MEA0406" base="decimal" maxLength="10" />
    <elementType name="MEA0407" base="string" minLength="2" maxLength="2" />
    <elementType name="MEA0408" base="decimal" maxLength="15" />
    <elementType name="MEA0409" base="decimal" maxLength="10" />
    <elementType name="MEA0410" base="string" minLength="2" maxLength="2" />
    <elementType name="MEA0411" base="decimal" maxLength="15" />
    <elementType name="MEA0412" base="decimal" maxLength="10" />
    <elementType name="MEA0413" base="string" minLength="2" maxLength="2" />
    <elementType name="MEA0414" base="decimal" maxLength="15" />
    <elementType name="MEA0415" base="decimal" maxLength="10" />
    <elementType name="MEA05" base="decimal" maxLength="20" />
    <elementType name="MEA06" base="decimal" maxLength="20" />
    <elementType name="MEA07" base="string" minLength="2" maxLength="2" />
    <elementType name="MEA08" base="string" minLength="2" maxLength="2" />
    <elementType name="MEA09" base="string" minLength="2" maxLength="2" />
    <elementType name="MEA10" base="string" minLength="2" maxLength="4" />
    <elementType name="MEA11" base="string" maxLength="3" />
    <elementType name="MEA12" base="string" maxLength="30" />
    <elementType name="N101" base="string" minLength="2" maxLength="3" />
    <elementType name="N102" base="string" maxLength="60" />
    <elementType name="N103" base="string" maxLength="2" />
    <elementType name="N104" base="string" minLength="2" maxLength="80" />
    <elementType name="N105" base="string" minLength="2" maxLength="2" />
    <elementType name="N106" base="string" minLength="2" maxLength="3" />
    <elementType name="N201" base="string" maxLength="60" />
    <elementType name="N202" base="string" maxLength="60" />
    <elementType name="N301" base="string" maxLength="55" />
    <elementType name="N302" base="string" maxLength="55" />
    <elementType name="N401" base="string" minLength="2" maxLength="30" />
    <elementType name="N402" base="string" minLength="2" maxLength="2" />
    <elementType name="N403" base="string" minLength="3" maxLength="15" />
    <elementType name="N404" base="string" minLength="2" maxLength="3" />
    <elementType name="N405" base="string" maxLength="2" />
    <elementType name="N406" base="string" maxLength="30" />
    <elementType name="N407" base="string" maxLength="3" />
    <elementType name="N901" base="string" minLength="2" maxLength="3" />
    <elementType name="N902" base="string" maxLength="80" />
    <elementType name="N903" base="string" maxLength="45" />
    <elementType name="N904" base="date" minLength="8" maxLength="8" />
    <elementType name="N905" base="time" minLength="4" maxLength="8" />
    <elementType name="N906" base="string" minLength="2" maxLength="2" />
    <elementType name="N90701" base="string" minLength="2" maxLength="3" />
    <elementType name="N90702" base="string" maxLength="80" />
    <elementType name="N90703" base="string" minLength="2" maxLength="3" />
    <elementType name="N90704" base="string" maxLength="80" />
    <elementType name="N90705" base="string" minLength="2" maxLength="3" />
    <elementType name="N90706" base="string" maxLength="80" />
    <elementType name="NTE01" base="string" minLength="3" maxLength="3" />
    <elementType name="NTE02" base="string" maxLength="80" />
    <elementType name="PAL01" base="string" maxLength="2" />
    <elementType name="PAL02" base="decimal" maxLength="3" />
    <elementType name="PAL03" base="decimal" maxLength="3" />
    <elementType name="PAL04" base="decimal" maxLength="6" />
    <elementType name="PAL05" base="decimal" maxLength="8" />
    <elementType name="PAL06" base="string" minLength="2" maxLength="2" />
    <elementType name="PAL07" base="decimal" maxLength="8" />
    <elementType name="PAL08" base="decimal" maxLength="8" />
    <elementType name="PAL09" base="decimal" maxLength="8" />
    <elementType name="PAL10" base="string" minLength="2" maxLength="2" />
    <elementType name="PAL11" base="decimal" maxLength="9" />
    <elementType name="PAL12" base="string" minLength="2" maxLength="2" />
    <elementType name="PAL13" base="decimal" maxLength="9" />
    <elementType name="PAL14" base="string" minLength="2" maxLength="2" />
    <elementType name="PAL15" base="string" />
    <elementType name="PAL16" base="decimal" maxLength="6" />
    <elementType name="PAL17" base="string" />
    <elementType name="PAL18" base="decimal" maxLength="15" />
    <elementType name="PID01" base="string" />
    <elementType name="PID02" base="string" minLength="2" maxLength="3" />
    <elementType name="PID03" base="string" minLength="2" maxLength="2" />
    <elementType name="PID04" base="string" maxLength="12" />
    <elementType name="PID05" base="string" maxLength="80" />
    <elementType name="PID06" base="string" minLength="2" maxLength="2" />
    <elementType name="PID07" base="string" maxLength="15" />
    <elementType name="PID08" base="string" />
    <elementType name="PID09" base="string" minLength="2" maxLength="3" />
    <elementType name="PKG01" base="string" />
    <elementType name="PKG02" base="string" maxLength="5" />
    <elementType name="PKG03" base="string" minLength="2" maxLength="2" />
    <elementType name="PKG04" base="string" maxLength="7" />
    <elementType name="PKG05" base="string" maxLength="80" />
    <elementType name="PKG06" base="string" minLength="2" maxLength="2" />
    <elementType name="QTY01" base="string" minLength="2" maxLength="2" />
    <elementType name="QTY02" base="decimal" maxLength="15" />
    <elementType name="QTY0301" base="string" minLength="2" maxLength="2" />
    <elementType name="QTY0302" base="decimal" maxLength="15" />
    <elementType name="QTY0303" base="decimal" maxLength="10" />
    <elementType name="QTY0304" base="string" minLength="2" maxLength="2" />
    <elementType name="QTY0305" base="decimal" maxLength="15" />
    <elementType name="QTY0306" base="decimal" maxLength="10" />
    <elementType name="QTY0307" base="string" minLength="2" maxLength="2" />
    <elementType name="QTY0308" base="decimal" maxLength="15" />
    <elementType name="QTY0309" base="decimal" maxLength="10" />
    <elementType name="QTY0310" base="string" minLength="2" maxLength="2" />
    <elementType name="QTY0311" base="decimal" maxLength="15" />
    <elementType name="QTY0312" base="decimal" maxLength="10" />
    <elementType name="QTY0313" base="string" minLength="2" maxLength="2" />
    <elementType name="QTY0314" base="decimal" maxLength="15" />
    <elementType name="QTY0315" base="decimal" maxLength="10" />
    <elementType name="QTY04" base="string" maxLength="30" />
    <elementType name="REF01" base="string" minLength="2" maxLength="3" />
    <elementType name="REF02" base="string" maxLength="80" />
    <elementType name="REF03" base="string" maxLength="80" />
    <elementType name="REF0401" base="string" minLength="2" maxLength="3" />
    <elementType name="REF0402" base="string" maxLength="80" />
    <elementType name="REF0403" base="string" minLength="2" maxLength="3" />
    <elementType name="REF0404" base="string" maxLength="80" />
    <elementType name="REF0405" base="string" minLength="2" maxLength="3" />
    <elementType name="REF0406" base="string" maxLength="80" />
    <elementType name="SLN01" base="string" maxLength="20" />
    <elementType name="SLN02" base="string" maxLength="20" />
    <elementType name="SLN03" base="string" />
    <elementType name="SLN04" base="decimal" maxLength="15" />
    <elementType name="SLN0501" base="string" minLength="2" maxLength="2" />
    <elementType name="SLN0502" base="decimal" maxLength="15" />
    <elementType name="SLN0503" base="decimal" maxLength="10" />
    <elementType name="SLN0504" base="string" minLength="2" maxLength="2" />
    <elementType name="SLN0505" base="decimal" maxLength="15" />
    <elementType name="SLN0506" base="decimal" maxLength="10" />
    <elementType name="SLN0507" base="string" minLength="2" maxLength="2" />
    <elementType name="SLN0508" base="decimal" maxLength="15" />
    <elementType name="SLN0509" base="decimal" maxLength="10" />
    <elementType name="SLN0510" base="string" minLength="2" maxLength="2" />
    <elementType name="SLN0511" base="decimal" maxLength="15" />
    <elementType name="SLN0512" base="decimal" maxLength="10" />
    <elementType name="SLN0513" base="string" minLength="2" maxLength="2" />
    <elementType name="SLN0514" base="decimal" maxLength="15" />
    <elementType name="SLN0515" base="decimal" maxLength="10" />
    <elementType name="SLN06" base="decimal" maxLength="17" />
    <elementType name="SLN07" base="string" minLength="2" maxLength="2" />
    <elementType name="SLN08" base="string" />
    <elementType name="SLN09" base="string" minLength="2" maxLength="2" />
    <elementType name="SLN10" base="string" maxLength="80" />
    <elementType name="SLN11" base="string" minLength="2" maxLength="2" />
    <elementType name="SLN12" base="string" maxLength="80" />
    <elementType name="SLN13" base="string" minLength="2" maxLength="2" />
    <elementType name="SLN14" base="string" maxLength="80" />
    <elementType name="SLN15" base="string" minLength="2" maxLength="2" />
    <elementType name="SLN16" base="string" maxLength="80" />
    <elementType name="SLN17" base="string" minLength="2" maxLength="2" />
    <elementType name="SLN18" base="string" maxLength="80" />
    <elementType name="SLN19" base="string" minLength="2" maxLength="2" />
    <elementType name="SLN20" base="string" maxLength="80" />
    <elementType name="SLN21" base="string" minLength="2" maxLength="2" />
    <elementType name="SLN22" base="string" maxLength="80" />
    <elementType name="SLN23" base="string" minLength="2" maxLength="2" />
    <elementType name="SLN24" base="string" maxLength="80" />
    <elementType name="SLN25" base="string" minLength="2" maxLength="2" />
    <elementType name="SLN26" base="string" maxLength="80" />
    <elementType name="SLN27" base="string" minLength="2" maxLength="2" />
    <elementType name="SLN28" base="string" maxLength="80" />
    <elementType name="TD101" base="string" minLength="3" maxLength="5" />
    <elementType name="TD102" base="decimal" maxLength="7" />
    <elementType name="TD103" base="string" />
    <elementType name="TD104" base="string" maxLength="30" />
    <elementType name="TD105" base="string" maxLength="50" />
    <elementType name="TD106" base="string" maxLength="2" />
    <elementType name="TD107" base="decimal" maxLength="10" />
    <elementType name="TD108" base="string" minLength="2" maxLength="2" />
    <elementType name="TD109" base="decimal" maxLength="8" />
    <elementType name="TD110" base="string" minLength="2" maxLength="2" />
    <elementType name="TD401" base="string" minLength="2" maxLength="3" />
    <elementType name="TD402" base="string" />
    <elementType name="TD403" base="string" maxLength="4" />
    <elementType name="TD404" base="string" maxLength="80" />
    <elementType name="TD405" base="string" />
    <elementType name="UIT0101" base="string" minLength="2" maxLength="2" />
    <elementType name="UIT0102" base="decimal" maxLength="15" />
    <elementType name="UIT0103" base="decimal" maxLength="10" />
    <elementType name="UIT0104" base="string" minLength="2" maxLength="2" />
    <elementType name="UIT0105" base="decimal" maxLength="15" />
    <elementType name="UIT0106" base="decimal" maxLength="10" />
    <elementType name="UIT0107" base="string" minLength="2" maxLength="2" />
    <elementType name="UIT0108" base="decimal" maxLength="15" />
    <elementType name="UIT0109" base="decimal" maxLength="10" />
    <elementType name="UIT0110" base="string" minLength="2" maxLength="2" />
    <elementType name="UIT0111" base="decimal" maxLength="15" />
    <elementType name="UIT0112" base="decimal" maxLength="10" />
    <elementType name="UIT0113" base="string" minLength="2" maxLength="2" />
    <elementType name="UIT0114" base="decimal" maxLength="15" />
    <elementType name="UIT0115" base="decimal" maxLength="10" />
    <elementType name="UIT02" base="decimal" maxLength="17" />
    <elementType name="UIT03" base="string" minLength="2" maxLength="2" />
    <elementType name="USI01" base="decimal" maxLength="15" />
    <elementType name="USI02" base="string" minLength="3" maxLength="3" />
    <elementType name="USI03" base="string" />
    <compositeType name="MEA04">
        <sequence>
            <element type="MEA0401" minOccurs="1" />
            <element type="MEA0402" />
            <element type="MEA0403" />
            <element type="MEA0404" />
            <element type="MEA0405" />
            <element type="MEA0406" />
            <element type="MEA0407" />
            <element type="MEA0408" />
            <element type="MEA0409" />
            <element type="MEA0410" />
            <element type="MEA0411" />
            <element type="MEA0412" />
            <element type="MEA0413" />
            <element type="MEA0414" />
            <element type="MEA0415" />
        </sequence>
    </compositeType>
    <compositeType name="N907">
        <sequence>
            <element type="N90701" minOccurs="1" />
            <element type="N90702" minOccurs="1" />
            <element type="N90703" />
            <element type="N90704" />
            <element type="N90705" />
            <element type="N90706" />
        </sequence>
    </compositeType>
    <compositeType name="QTY03">
        <sequence>
            <element type="QTY0301" minOccurs="1" />
            <element type="QTY0302" />
            <element type="QTY0303" />
            <element type="QTY0304" />
            <element type="QTY0305" />
            <element type="QTY0306" />
            <element type="QTY0307" />
            <element type="QTY0308" />
            <element type="QTY0309" />
            <element type="QTY0310" />
            <element type="QTY0311" />
            <element type="QTY0312" />
            <element type="QTY0313" />
            <element type="QTY0314" />
            <element type="QTY0315" />
        </sequence>
    </compositeType>
    <compositeType name="REF04">
        <sequence>
            <element type="REF0401" minOccurs="1" />
            <element type="REF0402" minOccurs="1" />
            <element type="REF0403" />
            <element type="REF0404" />
            <element type="REF0405" />
            <element type="REF0406" />
        </sequence>
    </compositeType>
    <compositeType name="SLN05">
        <sequence>
            <element type="SLN0501" minOccurs="1" />
            <element type="SLN0502" />
            <element type="SLN0503" />
            <element type="SLN0504" />
            <element type="SLN0505" />
            <element type="SLN0506" />
            <element type="SLN0507" />
            <element type="SLN0508" />
            <element type="SLN0509" />
            <element type="SLN0510" />
            <element type="SLN0511" />
            <element type="SLN0512" />
            <element type="SLN0513" />
            <element type="SLN0514" />
            <element type="SLN0515" />
        </sequence>
    </compositeType>
    <compositeType name="UIT01">
        <sequence>
            <element type="UIT0101" minOccurs="1" />
            <element type="UIT0102" />
            <element type="UIT0103" />
            <element type="UIT0104" />
            <element type="UIT0105" />
            <element type="UIT0106" />
            <element type="UIT0107" />
            <element type="UIT0108" />
            <element type="UIT0109" />
            <element type="UIT0110" />
            <element type="UIT0111" />
            <element type="UIT0112" />
            <element type="UIT0113" />
            <element type="UIT0114" />
            <element type="UIT0115" />
        </sequence>
    </compositeType>
    <segmentType name="BGN">
        <sequence>
            <element type="BGN01" minOccurs="1" />
            <element type="BGN02" minOccurs="1" />
            <element type="BGN03" minOccurs="1" />
            <element type="BGN04" />
            <element type="BGN05" />
            <element type="BGN06" />
            <element type="BGN07" />
            <element type="BGN08" />
            <element type="BGN09" />
        </sequence>
    </segmentType>
    <segmentType name="G22">
        <sequence>
            <element type="G2201" minOccurs="1" />
            <element type="G2202" />
            <element type="G2203" />
            <element type="G2204" />
            <element type="G2205" />
        </sequence>
    </segmentType>
    <segmentType name="G23">
        <sequence>
            <element type="G2301" minOccurs="1" />
            <element type="G2302" minOccurs="1" />
            <element type="G2303" />
            <element type="G2304" />
            <element type="G2305" />
            <element type="G2306" />
            <element type="G2307" />
            <element type="G2308" />
            <element type="G2309" />
            <element type="G2310" />
            <element type="G2311" />
            <element type="G2312" />
            <element type="G2313" />
            <element type="G2314" />
            <element type="G2315" />
            <element type="G2316" />
        </sequence>
    </segmentType>
    <segmentType name="G24">
        <sequence>
            <element type="G2401" minOccurs="1" />
        </sequence>
    </segmentType>
    <segmentType name="G26">
        <sequence>
            <element type="G2601" minOccurs="1" />
            <element type="G2602" />
            <element type="G2603" />
            <element type="G2604" />
            <element type="G2605" />
            <element type="G2606" />
        </sequence>
    </segmentType>
    <segmentType name="G36">
        <sequence>
            <element type="G3601" minOccurs="1" />
            <element type="G3602" />
            <element type="G3603" minOccurs="1" />
            <element type="G3604" />
        </sequence>
    </segmentType>
    <segmentType name="G39">
        <sequence>
            <element type="G3901" />
            <element type="G3902" />
            <element type="G3903" />
            <element type="G3904" />
            <element type="G3905" />
            <element type="G3906" />
            <element type="G3907" />
            <element type="G3908" />
            <element type="G3909" />
            <element type="G3910" />
            <element type="G3911" />
            <element type="G3912" />
            <element type="G3913" />
            <element type="G3914" />
            <element type="G3915" />
            <element type="G3916" />
            <element type="G3917" />
            <element type="G3918" />
            <element type="G3919" />
            <element type="G3920" />
            <element type="G3921" />
            <element type="G3922" />
            <element type="G3923" />
            <element type="G3924" />
            <element type="G3925" />
            <element type="G3926" />
            <element type="G3927" />
            <element type="G3928" />
            <element type="G3929" />
        </sequence>
    </segmentType>
    <segmentType name="G40">
        <sequence>
            <element type="G4001" />
            <element type="G4002" minOccurs="1" />
            <element type="G4003" />
            <element type="G4004" />
            <element type="G4005" />
            <element type="G4006" />
            <element type="G4007" />
            <element type="G4008" />
            <element type="G4009" />
        </sequence>
    </segmentType>
    <segmentType name="G43">
        <sequence>
            <element type="G4301" minOccurs="1" />
            <element type="G4302" />
            <element type="G4303" />
            <element type="G4304" />
        </sequence>
    </segmentType>
    <segmentType name="G46">
        <sequence>
            <element type="G4601" minOccurs="1" />
            <element type="G4602" minOccurs="1" />
            <element type="G4603" />
            <element type="G4604" />
            <element type="G4605" />
            <element type="G4606" />
            <element type="G4607" />
            <element type="G4608" />
            <element type="G4609" />
            <element type="G4610" />
            <element type="G4611" />
            <element type="G4612" />
        </sequence>
    </segmentType>
    <segmentType name="G53">
        <sequence>
            <element type="G5301" minOccurs="1" />
        </sequence>
    </segmentType>
    <segmentType name="G54">
        <sequence>
            <element type="G5401" minOccurs="1" />
            <element type="G5402" minOccurs="1" />
            <element type="G5403" />
            <element type="G5404" />
            <element type="G5405" />
            <element type="G5406" />
        </sequence>
    </segmentType>
    <segmentType name="G55">
        <sequence>
            <element type="G5501" minOccurs="1" />
            <element type="G5502" minOccurs="1" />
            <element type="G5503" />
            <element type="G5504" />
            <element type="G5505" />
            <element type="G5506" />
            <element type="G5507" />
            <element type="G5508" />
            <element type="G5509" />
            <element type="G5510" />
            <element type="G5511" />
            <element type="G5512" />
            <element type="G5513" />
            <element type="G5514" />
            <element type="G5515" />
            <element type="G5516" />
            <element type="G5517" />
            <element type="G5518" />
            <element type="G5519" />
            <element type="G5520" />
            <element type="G5521" />
            <element type="G5522" />
            <element type="G5523" />
            <element type="G5524" />
            <element type="G5525" />
            <element type="G5526" />
            <element type="G5527" />
            <element type="G5528" />
            <element type="G5529" />
            <element type="G5530" />
            <element type="G5531" />
            <element type="G5532" />
            <element type="G5533" />
        </sequence>
    </segmentType>
    <segmentType name="G61">
        <sequence>
            <element type="G6101" minOccurs="1" />
            <element type="G6102" minOccurs="1" />
            <element type="G6103" />
            <element type="G6104" />
            <element type="G6105" />
        </sequence>
    </segmentType>
    <segmentType name="G62">
        <sequence>
            <element type="G6201" />
            <element type="G6202" />
            <element type="G6203" />
            <element type="G6204" />
            <element type="G6205" />
        </sequence>
    </segmentType>
    <segmentType name="G69">
        <sequence>
            <element type="G6901" minOccurs="1" />
        </sequence>
    </segmentType>
    <segmentType name="G93">
        <sequence>
            <element type="G9301" />
            <element type="G9302" />
            <element type="G9303" />
            <element type="G9304" />
            <element type="G9305" />
            <element type="G9306" />
            <element type="G9307" />
            <element type="G9308" />
        </sequence>
    </segmentType>
    <segmentType name="H1">
        <sequence>
            <element type="H101" minOccurs="1" />
            <element type="H102" />
            <element type="H103" />
            <element type="H104" />
            <element type="H105" />
            <element type="H106" />
            <element type="H107" />
            <element type="H108" />
            <element type="H109" />
        </sequence>
    </segmentType>
    <segmentType name="LDT">
        <sequence>
            <element type="LDT01" minOccurs="1" />
            <element type="LDT02" minOccurs="1" />
            <element type="LDT03" minOccurs="1" />
            <element type="LDT04" />
        </sequence>
    </segmentType>
    <segmentType name="LIN">
        <sequence>
            <element type="LIN01" />
            <element type="LIN02" minOccurs="1" />
            <element type="LIN03" minOccurs="1" />
            <element type="LIN04" />
            <element type="LIN05" />
            <element type="LIN06" />
            <element type="LIN07" />
            <element type="LIN08" />
            <element type="LIN09" />
            <element type="LIN10" />
            <element type="LIN11" />
            <element type="LIN12" />
            <element type="LIN13" />
            <element type="LIN14" />
            <element type="LIN15" />
            <element type="LIN16" />
            <element type="LIN17" />
            <element type="LIN18" />
            <element type="LIN19" />
            <element type="LIN20" />
            <element type="LIN21" />
            <element type="LIN22" />
            <element type="LIN23" />
            <element type="LIN24" />
            <element type="LIN25" />
            <element type="LIN26" />
            <element type="LIN27" />
            <element type="LIN28" />
            <element type="LIN29" />
            <element type="LIN30" />
            <element type="LIN31" />
        </sequence>
    </segmentType>
    <segmentType name="LM">
        <sequence>
            <element type="LM01" minOccurs="1" />
            <element type="LM02" />
        </sequence>
    </segmentType>
    <segmentType name="LQ">
        <sequence>
            <element type="LQ01" />
            <element type="LQ02" />
        </sequence>
    </segmentType>
    <segmentType name="LX">
        <sequence>
            <element type="LX01" minOccurs="1" />
        </sequence>
    </segmentType>
    <segmentType name="MEA">
        <sequence>
            <element type="MEA01" />
            <element type="MEA02" />
            <element type="MEA03" />
            <composite type="MEA04" />
            <element type="MEA05" />
            <element type="MEA06" />
            <element type="MEA07" />
            <element type="MEA08" />
            <element type="MEA09" />
            <element type="MEA10" />
            <element type="MEA11" />
            <element type="MEA12" />
        </sequence>
    </segmentType>
    <segmentType name="N1">
        <sequence>
            <element type="N101" minOccurs="1" />
            <element type="N102" />
            <element type="N103" />
            <element type="N104" />
            <element type="N105" />
            <element type="N106" />
        </sequence>
    </segmentType>
    <segmentType name="N2">
        <sequence>
            <element type="N201" minOccurs="1" />
            <element type="N202" />
        </sequence>
    </segmentType>
    <segmentType name="N3">
        <sequence>
            <element type="N301" minOccurs="1" />
            <element type="N302" />
        </sequence>
    </segmentType>
    <segmentType name="N4">
        <sequence>
            <element type="N401" />
            <element type="N402" />
            <element type="N403" />
            <element type="N404" />
            <element type="N405" />
            <element type="N406" />
            <element type="N407" />
        </sequence>
    </segmentType>
    <segmentType name="N9">
        <sequence>
            <element type="N901" minOccurs="1" />
            <element type="N902" />
            <element type="N903" />
            <element type="N904" />
            <element type="N905" />
            <element type="N906" />
            <composite type="N907" />
        </sequence>
    </segmentType>
    <segmentType name="NTE">
        <sequence>
            <element type="NTE01" />
            <element type="NTE02" minOccurs="1" />
        </sequence>
    </segmentType>
    <segmentType name="PAL">
        <sequence>
            <element type="PAL01" />
            <element type="PAL02" />
            <element type="PAL03" />
            <element type="PAL04" />
            <element type="PAL05" />
            <element type="PAL06" />
            <element type="PAL07" />
            <element type="PAL08" />
            <element type="PAL09" />
            <element type="PAL10" />
            <element type="PAL11" />
            <element type="PAL12" />
            <element type="PAL13" />
            <element type="PAL14" />
            <element type="PAL15" />
            <element type="PAL16" />
            <element type="PAL17" />
            <element type="PAL18" />
        </sequence>
    </segmentType>
    <segmentType name="PID">
        <sequence>
            <element type="PID01" minOccurs="1" />
            <element type="PID02" />
            <element type="PID03" />
            <element type="PID04" />
            <element type="PID05" />
            <element type="PID06" />
            <element type="PID07" />
            <element type="PID08" />
            <element type="PID09" />
        </sequence>
    </segmentType>
    <segmentType name="PKG">
        <sequence>
            <element type="PKG01" />
            <element type="PKG02" />
            <element type="PKG03" />
            <element type="PKG04" />
            <element type="PKG05" />
            <element type="PKG06" />
        </sequence>
    </segmentType>
    <segmentType name="QTY">
        <sequence>
            <element type="QTY01" minOccurs="1" />
            <element type="QTY02" />
            <composite type="QTY03" />
            <element type="QTY04" />
        </sequence>
    </segmentType>
    <segmentType name="REF">
        <sequence>
            <element type="REF01" minOccurs="1" />
            <element type="REF02" />
            <element type="REF03" />
            <composite type="REF04" />
        </sequence>
    </segmentType>
    <segmentType name="SLN">
        <sequence>
            <element type="SLN01" minOccurs="1" />
            <element type="SLN02" />
            <element type="SLN03" minOccurs="1" />
            <element type="SLN04" />
            <composite type="SLN05" />
            <element type="SLN06" />
            <element type="SLN07" />
            <element type="SLN08" />
            <element type="SLN09" />
            <element type="SLN10" />
            <element type="SLN11" />
            <element type="SLN12" />
            <element type="SLN13" />
            <element type="SLN14" />
            <element type="SLN15" />
            <element type="SLN16" />
            <element type="SLN17" />
            <element type="SLN18" />
            <element type="SLN19" />
            <element type="SLN20" />
            <element type="SLN21" />
            <element type="SLN22" />
            <element type="SLN23" />
            <element type="SLN24" />
            <element type="SLN25" />
            <element type="SLN26" />
            <element type="SLN27" />
            <element type="SLN28" />
        </sequence>
    </segmentType>
    <segmentType name="TD1">
        <sequence>
            <element type="TD101" />
            <element type="TD102" />
            <element type="TD103" />
            <element type="TD104" />
            <element type="TD105" />
            <element type="TD106" />
            <element type="TD107" />
            <element type="TD108" />
            <element type="TD109" />
            <element type="TD110" />
        </sequence>
    </segmentType>
    <segmentType name="TD4">
        <sequence>
            <element type="TD401" />
            <element type="TD402" />
            <element type="TD403" />
            <element type="TD404" />
            <element type="TD405" />
        </sequence>
    </segmentType>
    <segmentType name="UIT">
        <sequence>
            <composite type="UIT01" minOccurs="1" />
            <element type="UIT02" />
            <element type="UIT03" />
        </sequence>
    </segmentType>
    <segmentType name="USI">
        <sequence>
            <element type="USI01" minOccurs="1" />
            <element type="USI02" minOccurs="1" />
            <element type="USI03" />
        </sequence>
    </segmentType>
</schema>
